README.md
__init__.py
client.cpython-312-x86_64-linux-gnu.so
da_client.cpython-312-x86_64-linux-gnu.so
gui.py
input_validation.cpython-312-x86_64-linux-gnu.so
requirements.txt
scct.py
server.cpython-312-x86_64-linux-gnu.so
start.cpython-312-x86_64-linux-gnu.so
scops2-0.0.9.5.dist-info/METADATA
scops2-0.0.9.5.dist-info/WHEEL
scops2-0.0.9.5.dist-info/entry_points.txt
scops2-0.0.9.5.dist-info/licenses/LICENSE
scops2-0.0.9.5.dist-info/RECORD
